[
  {
    "iso3": "AFG",
    "country": "Afghanistan",
    "overlooked_score": 0,
    "severity": "9.1",
    "population_in_need": 1829601505
  },
  {
    "iso3": "AGO",
    "country": "Angola",
    "overlooked_score": 0,
    "severity": "6.6",
    "population_in_need": 0
  },
  {
    "iso3": "BDI",
    "country": "Burundi",
    "overlooked_score": 0,
    "severity": "6.9",
    "population_in_need": 0
  },
  {
    "iso3": "BDI",
    "country": "Burundi",
    "overlooked_score": 0,
    "severity": "5.1",
    "population_in_need": 0
  },
  {
    "iso3": "BEN",
    "country": "Benin",
    "overlooked_score": 0,
    "severity": "4.3",
    "population_in_need": 0
  },
  {
    "iso3": "BFA",
    "country": "Burkina Faso",
    "overlooked_score": 0,
    "severity": "8.4",
    "population_in_need": 221484949
  },
  {
    "iso3": "BGD",
    "country": "Bangladesh",
    "overlooked_score": 0,
    "severity": "6.3",
    "population_in_need": 0
  },
  {
    "iso3": "BGD",
    "country": "Bangladesh",
    "overlooked_score": 0,
    "severity": "6.5",
    "population_in_need": 0
  },
  {
    "iso3": "BRA",
    "country": "Brazil",
    "overlooked_score": 0,
    "severity": "5.1",
    "population_in_need": 0
  },
  {
    "iso3": "CAF",
    "country": "CAR",
    "overlooked_score": 0,
    "severity": "7.9",
    "population_in_need": 67595320
  },
  {
    "iso3": "CHL",
    "country": "Chile",
    "overlooked_score": 0,
    "severity": "5.1",
    "population_in_need": 0
  },
  {
    "iso3": "CIV",
    "country": "C\u00f4te d'Ivoire",
    "overlooked_score": 0,
    "severity": "4.3",
    "population_in_need": 0
  },
  {
    "iso3": "CMR",
    "country": "Cameroon",
    "overlooked_score": 0,
    "severity": "7.2",
    "population_in_need": 201858835
  },
  {
    "iso3": "CMR",
    "country": "Cameroon",
    "overlooked_score": 0,
    "severity": "7.4",
    "population_in_need": 201858835
  },
  {
    "iso3": "CMR",
    "country": "Cameroon",
    "overlooked_score": 0,
    "severity": "5.2",
    "population_in_need": 201858835
  },
  {
    "iso3": "COD",
    "country": "DRC",
    "overlooked_score": 0,
    "severity": "8.9",
    "population_in_need": 915901388
  },
  {
    "iso3": "COL",
    "country": "Colombia",
    "overlooked_score": 0,
    "severity": "8.3",
    "population_in_need": 168414509
  },
  {
    "iso3": "COL",
    "country": "Colombia",
    "overlooked_score": 0,
    "severity": "6.7",
    "population_in_need": 168414509
  },
  {
    "iso3": "CRI",
    "country": "Costa Rica",
    "overlooked_score": 0,
    "severity": "4",
    "population_in_need": 0
  },
  {
    "iso3": "CRI",
    "country": "Costa Rica",
    "overlooked_score": 0,
    "severity": "3.5",
    "population_in_need": 0
  },
  {
    "iso3": "CUB",
    "country": "Cuba",
    "overlooked_score": 0,
    "severity": "6.1",
    "population_in_need": 0
  },
  {
    "iso3": "CUB",
    "country": "Cuba",
    "overlooked_score": 0,
    "severity": "6.5",
    "population_in_need": 0
  },
  {
    "iso3": "DJI",
    "country": "Djibouti",
    "overlooked_score": 0,
    "severity": "4.5",
    "population_in_need": 0
  },
  {
    "iso3": "DJI",
    "country": "Djibouti",
    "overlooked_score": 0,
    "severity": "5.4",
    "population_in_need": 0
  },
  {
    "iso3": "DOM",
    "country": "Dominican Republic",
    "overlooked_score": 0,
    "severity": "4.1",
    "population_in_need": 0
  },
  {
    "iso3": "DZA",
    "country": "Algeria",
    "overlooked_score": 0,
    "severity": "5.3",
    "population_in_need": 0
  },
  {
    "iso3": "DZA",
    "country": "Algeria",
    "overlooked_score": 0,
    "severity": "5.2",
    "population_in_need": 0
  },
  {
    "iso3": "ECU",
    "country": "Ecuador",
    "overlooked_score": 0,
    "severity": "5.5",
    "population_in_need": 0
  },
  {
    "iso3": "ECU",
    "country": "Ecuador",
    "overlooked_score": 0,
    "severity": "6.7",
    "population_in_need": 0
  },
  {
    "iso3": "ECU",
    "country": "Ecuador",
    "overlooked_score": 0,
    "severity": "4.4",
    "population_in_need": 0
  },
  {
    "iso3": "EGY",
    "country": "Egypt",
    "overlooked_score": 0,
    "severity": "5.6",
    "population_in_need": 0
  },
  {
    "iso3": "ERI",
    "country": "Eritrea",
    "overlooked_score": 0,
    "severity": "5.9",
    "population_in_need": 0
  },
  {
    "iso3": "ESP",
    "country": "Spain",
    "overlooked_score": 0,
    "severity": "3.5",
    "population_in_need": 0
  },
  {
    "iso3": "ETH",
    "country": "Ethiopia",
    "overlooked_score": 0,
    "severity": "6.4",
    "population_in_need": 0
  },
  {
    "iso3": "ETH",
    "country": "Ethiopia",
    "overlooked_score": 0,
    "severity": "8.3",
    "population_in_need": 0
  },
  {
    "iso3": "GRC",
    "country": "Greece",
    "overlooked_score": 0,
    "severity": "4.5",
    "population_in_need": 0
  },
  {
    "iso3": "GTM",
    "country": "Guatemala",
    "overlooked_score": 0,
    "severity": "7",
    "population_in_need": 45292585
  },
  {
    "iso3": "HND",
    "country": "Honduras",
    "overlooked_score": 0,
    "severity": "6.6",
    "population_in_need": 37876501
  },
  {
    "iso3": "HTI",
    "country": "Haiti",
    "overlooked_score": 0,
    "severity": "8.7",
    "population_in_need": 209004120
  },
  {
    "iso3": "IDN",
    "country": "Indonesia",
    "overlooked_score": 0,
    "severity": "5.4",
    "population_in_need": 0
  },
  {
    "iso3": "IDN",
    "country": "Indonesia",
    "overlooked_score": 0,
    "severity": "4.3",
    "population_in_need": 0
  },
  {
    "iso3": "IND",
    "country": "India",
    "overlooked_score": 0,
    "severity": "x",
    "population_in_need": 0
  },
  {
    "iso3": "IRN",
    "country": "Iran",
    "overlooked_score": 0,
    "severity": "7.9",
    "population_in_need": 0
  },
  {
    "iso3": "IRN",
    "country": "Iran",
    "overlooked_score": 0,
    "severity": "7.4",
    "population_in_need": 0
  },
  {
    "iso3": "IRQ",
    "country": "Iraq",
    "overlooked_score": 0,
    "severity": "6.7",
    "population_in_need": 0
  },
  {
    "iso3": "ITA",
    "country": "Italy",
    "overlooked_score": 0,
    "severity": "3.9",
    "population_in_need": 0
  },
  {
    "iso3": "JAM",
    "country": "Jamaica",
    "overlooked_score": 0,
    "severity": "5.2",
    "population_in_need": 0
  },
  {
    "iso3": "JOR",
    "country": "Jordan",
    "overlooked_score": 0,
    "severity": "5.9",
    "population_in_need": 0
  },
  {
    "iso3": "KEN",
    "country": "Kenya",
    "overlooked_score": 0,
    "severity": "5.6",
    "population_in_need": 0
  },
  {
    "iso3": "KEN",
    "country": "Kenya",
    "overlooked_score": 0,
    "severity": "6.5",
    "population_in_need": 0
  },
  {
    "iso3": "KHM",
    "country": "Cambodia",
    "overlooked_score": 0,
    "severity": "3.9",
    "population_in_need": 0
  },
  {
    "iso3": "LBN",
    "country": "Lebanon",
    "overlooked_score": 0,
    "severity": "6",
    "population_in_need": 0
  },
  {
    "iso3": "LBN",
    "country": "Lebanon",
    "overlooked_score": 0,
    "severity": "7.5",
    "population_in_need": 0
  },
  {
    "iso3": "LBY",
    "country": "Libya",
    "overlooked_score": 0,
    "severity": "6.4",
    "population_in_need": 0
  },
  {
    "iso3": "LBY",
    "country": "Libya",
    "overlooked_score": 0,
    "severity": "6.3",
    "population_in_need": 0
  },
  {
    "iso3": "LKA",
    "country": "Sri Lanka",
    "overlooked_score": 0,
    "severity": "6.2",
    "population_in_need": 0
  },
  {
    "iso3": "LSO",
    "country": "Lesotho",
    "overlooked_score": 0,
    "severity": "4.7",
    "population_in_need": 0
  },
  {
    "iso3": "MAR",
    "country": "Morocco",
    "overlooked_score": 0,
    "severity": "3.3",
    "population_in_need": 0
  },
  {
    "iso3": "MAR",
    "country": "Morocco",
    "overlooked_score": 0,
    "severity": "4.9",
    "population_in_need": 0
  },
  {
    "iso3": "MDG",
    "country": "Madagascar",
    "overlooked_score": 0,
    "severity": "5.8",
    "population_in_need": 0
  },
  {
    "iso3": "MDG",
    "country": "Madagascar",
    "overlooked_score": 0,
    "severity": "5.1",
    "population_in_need": 0
  },
  {
    "iso3": "MEX",
    "country": "Mexico",
    "overlooked_score": 0,
    "severity": "5.6",
    "population_in_need": 0
  },
  {
    "iso3": "MLI",
    "country": "Mali",
    "overlooked_score": 0,
    "severity": "8.3",
    "population_in_need": 145370528
  },
  {
    "iso3": "MMR",
    "country": "Myanmar",
    "overlooked_score": 0,
    "severity": "8.8",
    "population_in_need": 1199500984
  },
  {
    "iso3": "MOZ",
    "country": "Mozambique",
    "overlooked_score": 0,
    "severity": "6.9",
    "population_in_need": 37789917
  },
  {
    "iso3": "MOZ",
    "country": "Mozambique",
    "overlooked_score": 0,
    "severity": "5.8",
    "population_in_need": 37789917
  },
  {
    "iso3": "MRT",
    "country": "Mauritania",
    "overlooked_score": 0,
    "severity": "5.2",
    "population_in_need": 0
  },
  {
    "iso3": "MRT",
    "country": "Mauritania",
    "overlooked_score": 0,
    "severity": "5.2",
    "population_in_need": 0
  },
  {
    "iso3": "MWI",
    "country": "Malawi",
    "overlooked_score": 0,
    "severity": "6.5",
    "population_in_need": 0
  },
  {
    "iso3": "MYS",
    "country": "Malaysia",
    "overlooked_score": 0,
    "severity": "4",
    "population_in_need": 0
  },
  {
    "iso3": "NAM",
    "country": "Namibia",
    "overlooked_score": 0,
    "severity": "5.5",
    "population_in_need": 0
  },
  {
    "iso3": "NER",
    "country": "Niger",
    "overlooked_score": 0,
    "severity": "7.2",
    "population_in_need": 52133591
  },
  {
    "iso3": "NGA",
    "country": "Nigeria",
    "overlooked_score": 0,
    "severity": "8.4",
    "population_in_need": 234175308
  },
  {
    "iso3": "NGA",
    "country": "Nigeria",
    "overlooked_score": 0,
    "severity": "7.4",
    "population_in_need": 234175308
  },
  {
    "iso3": "NGA",
    "country": "Nigeria",
    "overlooked_score": 0,
    "severity": "4.3",
    "population_in_need": 234175308
  },
  {
    "iso3": "NGA",
    "country": "Nigeria",
    "overlooked_score": 0,
    "severity": "7.1",
    "population_in_need": 234175308
  },
  {
    "iso3": "PAK",
    "country": "Pakistan",
    "overlooked_score": 0,
    "severity": "x",
    "population_in_need": 0
  },
  {
    "iso3": "PAK",
    "country": "Pakistan",
    "overlooked_score": 0,
    "severity": "8.3",
    "population_in_need": 0
  },
  {
    "iso3": "PAK",
    "country": "Pakistan",
    "overlooked_score": 0,
    "severity": "7.3",
    "population_in_need": 0
  },
  {
    "iso3": "PAN",
    "country": "Panama",
    "overlooked_score": 0,
    "severity": "4",
    "population_in_need": 0
  },
  {
    "iso3": "PER",
    "country": "Peru",
    "overlooked_score": 0,
    "severity": "6",
    "population_in_need": 0
  },
  {
    "iso3": "PHL",
    "country": "Philippines",
    "overlooked_score": 0,
    "severity": "4.1",
    "population_in_need": 0
  },
  {
    "iso3": "PHL",
    "country": "Philippines",
    "overlooked_score": 0,
    "severity": "5.3",
    "population_in_need": 0
  },
  {
    "iso3": "PHL",
    "country": "Philippines",
    "overlooked_score": 0,
    "severity": "3.3",
    "population_in_need": 0
  },
  {
    "iso3": "PSE",
    "country": "Palestine",
    "overlooked_score": 0,
    "severity": "7.2",
    "population_in_need": 0
  },
  {
    "iso3": "PSE",
    "country": "Palestine",
    "overlooked_score": 0,
    "severity": "8.1",
    "population_in_need": 0
  },
  {
    "iso3": "RWA",
    "country": "Rwanda",
    "overlooked_score": 0,
    "severity": "4.9",
    "population_in_need": 0
  },
  {
    "iso3": "SDN",
    "country": "Sudan",
    "overlooked_score": 0,
    "severity": "9.6",
    "population_in_need": 1624238594
  },
  {
    "iso3": "SLV",
    "country": "El Salvador",
    "overlooked_score": 0,
    "severity": "5.7",
    "population_in_need": 21040587
  },
  {
    "iso3": "SOM",
    "country": "Somalia",
    "overlooked_score": 0,
    "severity": "8.6",
    "population_in_need": 141650172
  },
  {
    "iso3": "SOM",
    "country": "Somalia",
    "overlooked_score": 0,
    "severity": "4.1",
    "population_in_need": 141650172
  },
  {
    "iso3": "SSD",
    "country": "South Sudan",
    "overlooked_score": 0,
    "severity": "9.3",
    "population_in_need": 281905475
  },
  {
    "iso3": "SSD",
    "country": "South Sudan",
    "overlooked_score": 0,
    "severity": "7.4",
    "population_in_need": 281905475
  },
  {
    "iso3": "SWZ",
    "country": "Eswatini",
    "overlooked_score": 0,
    "severity": "4.9",
    "population_in_need": 0
  },
  {
    "iso3": "SYR",
    "country": "Syria",
    "overlooked_score": 0,
    "severity": "8.9",
    "population_in_need": 0
  },
  {
    "iso3": "TCD",
    "country": "Chad",
    "overlooked_score": 0,
    "severity": "8.2",
    "population_in_need": 110090207
  },
  {
    "iso3": "TCD",
    "country": "Chad",
    "overlooked_score": 0,
    "severity": "6.6",
    "population_in_need": 110090207
  },
  {
    "iso3": "TCD",
    "country": "Chad",
    "overlooked_score": 0,
    "severity": "4.6",
    "population_in_need": 110090207
  },
  {
    "iso3": "TCD",
    "country": "Chad",
    "overlooked_score": 0,
    "severity": "6",
    "population_in_need": 110090207
  },
  {
    "iso3": "TGO",
    "country": "Togo",
    "overlooked_score": 0,
    "severity": "4.3",
    "population_in_need": 0
  },
  {
    "iso3": "THA",
    "country": "Thailand",
    "overlooked_score": 0,
    "severity": "4.2",
    "population_in_need": 0
  },
  {
    "iso3": "THA",
    "country": "Thailand",
    "overlooked_score": 0,
    "severity": "5.2",
    "population_in_need": 0
  },
  {
    "iso3": "TTO",
    "country": "Trinidad and Tobago",
    "overlooked_score": 0,
    "severity": "3",
    "population_in_need": 0
  },
  {
    "iso3": "TUN",
    "country": "Tunisia",
    "overlooked_score": 0,
    "severity": "3.7",
    "population_in_need": 0
  },
  {
    "iso3": "TUR",
    "country": "T\u00fcrkiye",
    "overlooked_score": 0,
    "severity": "6.7",
    "population_in_need": 0
  },
  {
    "iso3": "TUR",
    "country": "T\u00fcrkiye",
    "overlooked_score": 0,
    "severity": "5.7",
    "population_in_need": 0
  },
  {
    "iso3": "TZA",
    "country": "Tanzania",
    "overlooked_score": 0,
    "severity": "4.9",
    "population_in_need": 0
  },
  {
    "iso3": "TZA",
    "country": "Tanzania",
    "overlooked_score": 0,
    "severity": "4.9",
    "population_in_need": 0
  },
  {
    "iso3": "UGA",
    "country": "Uganda",
    "overlooked_score": 0,
    "severity": "5.9",
    "population_in_need": 0
  },
  {
    "iso3": "UKR",
    "country": "Ukraine",
    "overlooked_score": 0,
    "severity": "9.2",
    "population_in_need": 523559204
  },
  {
    "iso3": "VEN",
    "country": "Venezuela",
    "overlooked_score": 0,
    "severity": "7.5",
    "population_in_need": 117424346
  },
  {
    "iso3": "YEM",
    "country": "Yemen",
    "overlooked_score": 0,
    "severity": "9.2",
    "population_in_need": 748340877
  },
  {
    "iso3": "YEM",
    "country": "Yemen",
    "overlooked_score": 0,
    "severity": "5.9",
    "population_in_need": 748340877
  },
  {
    "iso3": "ZMB",
    "country": "Zambia",
    "overlooked_score": 0,
    "severity": "6.4",
    "population_in_need": 0
  },
  {
    "iso3": "ZWE",
    "country": "Zimbabwe",
    "overlooked_score": 0,
    "severity": "7.1",
    "population_in_need": 0
  },
  {
    "iso3": "BDI",
    "country": "Burundi",
    "overlooked_score": 0,
    "severity": "7.1",
    "population_in_need": 0
  },
  {
    "iso3": "BGD",
    "country": "Bangladesh",
    "overlooked_score": 0,
    "severity": "6.8",
    "population_in_need": 0
  },
  {
    "iso3": "CMR",
    "country": "Cameroon",
    "overlooked_score": 0,
    "severity": "7.9",
    "population_in_need": 201858835
  },
  {
    "iso3": "COL",
    "country": "Colombia",
    "overlooked_score": 0,
    "severity": "8.4",
    "population_in_need": 168414509
  },
  {
    "iso3": "CUB",
    "country": "Cuba",
    "overlooked_score": 0,
    "severity": "6.6",
    "population_in_need": 0
  },
  {
    "iso3": "DJI",
    "country": "Djibouti",
    "overlooked_score": 0,
    "severity": "5.8",
    "population_in_need": 0
  },
  {
    "iso3": "DZA",
    "country": "Algeria",
    "overlooked_score": 0,
    "severity": "5.6",
    "population_in_need": 0
  },
  {
    "iso3": "ECU",
    "country": "Ecuador",
    "overlooked_score": 0,
    "severity": "7",
    "population_in_need": 0
  },
  {
    "iso3": "ETH",
    "country": "Ethiopia",
    "overlooked_score": 0,
    "severity": "8.6",
    "population_in_need": 0
  },
  {
    "iso3": "IDN",
    "country": "Indonesia",
    "overlooked_score": 0,
    "severity": "5.6",
    "population_in_need": 0
  },
  {
    "iso3": "IRN",
    "country": "Iran",
    "overlooked_score": 0,
    "severity": "7.8",
    "population_in_need": 0
  },
  {
    "iso3": "KEN",
    "country": "Kenya",
    "overlooked_score": 0,
    "severity": "6.7",
    "population_in_need": 0
  },
  {
    "iso3": "LBY",
    "country": "Libya",
    "overlooked_score": 0,
    "severity": "7.2",
    "population_in_need": 0
  },
  {
    "iso3": "MAR",
    "country": "Morocco",
    "overlooked_score": 0,
    "severity": "5.2",
    "population_in_need": 0
  },
  {
    "iso3": "MOZ",
    "country": "Mozambique",
    "overlooked_score": 0,
    "severity": "7.1",
    "population_in_need": 37789917
  },
  {
    "iso3": "MRT",
    "country": "Mauritania",
    "overlooked_score": 0,
    "severity": "6.1",
    "population_in_need": 0
  },
  {
    "iso3": "NGA",
    "country": "Nigeria",
    "overlooked_score": 0,
    "severity": "8.3",
    "population_in_need": 234175308
  },
  {
    "iso3": "PAK",
    "country": "Pakistan",
    "overlooked_score": 0,
    "severity": "8",
    "population_in_need": 0
  },
  {
    "iso3": "PHL",
    "country": "Philippines",
    "overlooked_score": 0,
    "severity": "5.8",
    "population_in_need": 0
  },
  {
    "iso3": "PSE",
    "country": "Palestine",
    "overlooked_score": 0,
    "severity": "8.5",
    "population_in_need": 0
  },
  {
    "iso3": "THA",
    "country": "Thailand",
    "overlooked_score": 0,
    "severity": "5.6",
    "population_in_need": 0
  },
  {
    "iso3": "TUR",
    "country": "T\u00fcrkiye",
    "overlooked_score": 0,
    "severity": "6.9",
    "population_in_need": 0
  },
  {
    "iso3": "TZA",
    "country": "Tanzania",
    "overlooked_score": 0,
    "severity": "5.5",
    "population_in_need": 0
  }
]